kdl_pre_built/__init__.py
kdl_pre_built/layers/__init__.py
kdl_pre_built/layers/gmplp.py
kdl_pre_built-0.1.1.dist-info/METADATA
kdl_pre_built-0.1.1.dist-info/WHEEL
kdl_pre_built-0.1.1.dist-info/RECORD
