Metadata-Version: 2.3
Name: kdl-pre-built
Version: 0.1.1
Summary: Nothing
License: MIT
Author: hvn-ai
Author-email: hoangvannamai@gmail.com
Requires-Python: >=3.12
Classifier: License :: OSI Approved :: MIT License
Classifier: Programming Language :: Python :: 3
Classifier: Programming Language :: Python :: 3.12
Classifier: Programming Language :: Python :: 3.13
Requires-Dist: tensorflow (>=2.19.0,<3.0.0)
